polidoro_question/__init__.py
polidoro_question/question.py
polidoro_question-1.0.1.1.dist-info/LICENSE
polidoro_question-1.0.1.1.dist-info/METADATA
polidoro_question-1.0.1.1.dist-info/WHEEL
polidoro_question-1.0.1.1.dist-info/top_level.txt
polidoro_question-1.0.1.1.dist-info/RECORD
