Metadata-Version: 2.1
Name: polidoro-question
Version: 1.0.1.1
Summary: Polidoro Question.
Home-page: https://github.com/heitorpolidoro/polidoro-question
Author: Heitor Polidoro
License: unlicense
Platform: UNKNOWN
Classifier: Programming Language :: Python :: 3
Classifier: License :: OSI Approved :: MIT License
Classifier: Operating System :: OS Independent
License-File: LICENSE
Requires-Dist: polidoro-terminal (<=1.0)
Requires-Dist: python-dateutil (==2.8.2)
